{
  "PLDC": {
    "total": 269,
    "covered": 258,
    "missing": 11,
    "oneCorrect": 269,
    "missingList": [
      {
        "lesson": 2,
        "question": 7
      },
      {
        "lesson": 3,
        "question": 9
      },
      {
        "lesson": 5,
        "question": 20
      },
      {
        "lesson": 6,
        "question": 8
      },
      {
        "lesson": 7,
        "question": 21
      },
      {
        "lesson": 7,
        "question": 23
      },
      {
        "lesson": 7,
        "question": 29
      },
      {
        "lesson": 8,
        "question": 21
      },
      {
        "lesson": 8,
        "question": 25
      },
      {
        "lesson": 9,
        "question": 24
      },
      {
        "lesson": 9,
        "question": 29
      }
    ]
  },
  "QTH": {
    "total": 268,
    "covered": 244,
    "missing": 24,
    "oneCorrect": 268,
    "missingList": [
      {
        "lesson": 1,
        "question": 5
      },
      {
        "lesson": 1,
        "question": 19
      },
      {
        "lesson": 2,
        "question": 5
      },
      {
        "lesson": 2,
        "question": 8
      },
      {
        "lesson": 2,
        "question": 14
      },
      {
        "lesson": 2,
        "question": 21
      },
      {
        "lesson": 3,
        "question": 20
      },
      {
        "lesson": 4,
        "question": 20
      },
      {
        "lesson": 5,
        "question": 22
      },
      {
        "lesson": 6,
        "question": 2
      },
      {
        "lesson": 6,
        "question": 27
      },
      {
        "lesson": 6,
        "question": 28
      },
      {
        "lesson": 7,
        "question": 22
      },
      {
        "lesson": 8,
        "question": 2
      },
      {
        "lesson": 8,
        "question": 9
      },
      {
        "lesson": 8,
        "question": 16
      },
      {
        "lesson": 8,
        "question": 21
      },
      {
        "lesson": 8,
        "question": 23
      },
      {
        "lesson": 8,
        "question": 26
      },
      {
        "lesson": 8,
        "question": 27
      },
      {
        "lesson": 8,
        "question": 28
      },
      {
        "lesson": 9,
        "question": 11
      },
      {
        "lesson": 9,
        "question": 13
      },
      {
        "lesson": 9,
        "question": 24
      }
    ]
  },
  "TMDT": {
    "total": 269,
    "covered": 245,
    "missing": 24,
    "oneCorrect": 269,
    "missingList": [
      {
        "lesson": 1,
        "question": 4
      },
      {
        "lesson": 1,
        "question": 15
      },
      {
        "lesson": 1,
        "question": 19
      },
      {
        "lesson": 2,
        "question": 23
      },
      {
        "lesson": 2,
        "question": 24
      },
      {
        "lesson": 3,
        "question": 9
      },
      {
        "lesson": 3,
        "question": 10
      },
      {
        "lesson": 3,
        "question": 14
      },
      {
        "lesson": 4,
        "question": 5
      },
      {
        "lesson": 4,
        "question": 11
      },
      {
        "lesson": 4,
        "question": 12
      },
      {
        "lesson": 4,
        "question": 23
      },
      {
        "lesson": 4,
        "question": 24
      },
      {
        "lesson": 5,
        "question": 5
      },
      {
        "lesson": 5,
        "question": 7
      },
      {
        "lesson": 5,
        "question": 18
      },
      {
        "lesson": 5,
        "question": 25
      },
      {
        "lesson": 6,
        "question": 9
      },
      {
        "lesson": 7,
        "question": 24
      },
      {
        "lesson": 8,
        "question": 14
      },
      {
        "lesson": 8,
        "question": 22
      },
      {
        "lesson": 9,
        "question": 3
      },
      {
        "lesson": 9,
        "question": 14
      },
      {
        "lesson": 9,
        "question": 28
      }
    ]
  }
}